LICENSE
MANIFEST.in
README.md
setup.py
tests/unwrap_test.py
tests/unwrap_test.py~
unwrapper/__init__.py
unwrapper/application.py
unwrapper/bin.py
unwrapper.egg-info/PKG-INFO
unwrapper.egg-info/SOURCES.txt
unwrapper.egg-info/dependency_links.txt
unwrapper.egg-info/entry_points.txt
unwrapper.egg-info/pbr.json
unwrapper.egg-info/requires.txt
unwrapper.egg-info/top_level.txt